[
    {
        "grade": 10,
        "card": 1,
        "description": "Понятие о механическом движении. Равнопеременное движение"
    },
    {
        "grade": 10,
        "card": 2,
        "description": "1 и 2 законы Ньютона. 3 Закон Ньютона"
    },
    {
        "grade": 10,
        "card": 3,
        "description": "Силы природы. Закон всемирного тяготения"
    },
    {
        "grade": 10,
        "card": 4,
        "description": "Кинематика криволинейного движения. Движение по окружности"
    },
    {
        "grade": 10,
        "card": 5,
        "description": "Давление. Атмосферное давление. Законы Паскаля, Архимеда и Бернулли"
    },
    {
        "grade": 10,
        "card": "6+7",
        "description": "Закон сохранения импульса. Механическая работа и мощность"
    },
    {
        "grade": 10,
        "card": "8+9",
        "description": "Энергия. Статика. Условия равновесия тел"
    },
    {
        "grade": 10,
        "card": "10-1",
        "description": "Основные положения МКТ. 1 положение"
    },
    {
        "grade": 10,
        "card": "10-2",
        "description": "Основные положения МКТ. 2 и 3 положения"
    },
    {
        "grade": 10,
        "card": 11,
        "description": "Строение твердых, жидких и газообразных тел. МКТ идеального газа"
    },
    {
        "grade": 10,
        "card": 12,
        "description": "Газовые законы"
    },
    {
        "grade": 10,
        "card": 13,
        "description": "Внутренняя энергия. Работа в термодинамике. 1 закон термодинамики. Тепловые двигатели"
    },
    {
        "grade": 10,
        "card": 14,
        "description": "Взаимное превращение жидкостей и газов"
    },
    {
        "grade": 10,
        "card": 15,
        "description": "Поверхностное натяжение. Смачивание. Капилярность"
    },
    {
        "grade": 10,
        "card": 16,
        "description": "Свойства твердых тел"
    },
    {
        "grade": 10,
        "card": 17,
        "description": "Электростатика. Часть 1"
    },
    {
        "grade": 10,
        "card": 18,
        "description": "Электростатика. Часть 2"
    },
    {
        "grade": 10,
        "card": 19,
        "description": "Электростатика. Часть 3"
    },
    {
        "grade": 10,
        "card": 20,
        "description": "Электрический ток. Закон Ома. Зависимость R(t)"
    },
    {
        "grade": 10,
        "card": 21,
        "description": "Соединение проводников. ЭДС. Закон Ома для замкнутой цепи"
    },
    {
        "grade": 10,
        "card": 22,
        "description": "Ток в полупроводниках. Ток в вакууме. ТЭЭ"
    },
    {
        "grade": 10,
        "card": 23,
        "description": "Электрический ток в электролитах. Электрический ток в газах"
    },
    {
        "grade": 11,
        "card": 1,
        "description": "Магнитное поле тока"
    },
    {
        "grade": 11,
        "card": 2,
        "description": "Явление ЭМИ"
    },
    {
        "grade": 11,
        "card": 3,
        "description": "Механические колебания"
    },
    {
        "grade": 11,
        "card": 4,
        "description": "Электрические колебания. Переменный электрический ток"
    },
    {
        "grade": 11,
        "card": 5,
        "description": "Емкость и индуктивность в цепи переменного тока"
    },
    {
        "grade": 11,
        "card": 6,
        "description": "Транзистор. Трансформатор"
    },
    {
        "grade": 11,
        "card": 7,
        "description": "Производство электрической энергии"
    },
    {
        "grade": 11,
        "card": 8,
        "description": "Механические волны"
    },
    {
        "grade": 11,
        "card": 9,
        "description": "Электромагнитное поле. Электромагнитные волны"
    },
    {
        "grade": 11,
        "card": 10,
        "description": "Развитие взглядов на природу света"
    },
    {
        "grade": 11,
        "card": 11,
        "description": "Преломление света"
    },
    {
        "grade": 11,
        "card": 12,
        "description": "Линзы"
    },
    {
        "grade": 11,
        "card": 13,
        "description": "Оптические приборы"
    },
    {
        "grade": 11,
        "card": 14,
        "description": "Световые волны"
    },
    {
        "grade": 11,
        "card": 15,
        "description": "Теория относительности"
    },
    {
        "grade": 11,
        "card": 16,
        "description": "Спектры. Спектральный анализ. Шкала электромагнитных волн"
    },
    {
        "grade": 11,
        "card": 17,
        "description": "Фотоэффект"
    },
    {
        "grade": 11,
        "card": 18,
        "description": "Строение атома"
    },
    {
        "grade": 11,
        "card": 19,
        "description": "Физика атомного ядра"
    },
    {
        "grade": 11,
        "card": 20,
        "description": "Энергия связи ядер. Цепные ядерные реакции"
    }
]
